pytest_xfaillist/__init__.py
pytest_xfaillist/generate.py
pytest_xfaillist/hooks.py
pytest_xfaillist/hooks_test.py
pytest_xfaillist-0.1.1.dist-info/entry_points.txt
pytest_xfaillist-0.1.1.dist-info/LICENSE
pytest_xfaillist-0.1.1.dist-info/WHEEL
pytest_xfaillist-0.1.1.dist-info/METADATA
pytest_xfaillist-0.1.1.dist-info/RECORD
